dagstream/__init__.py
dagstream/dagstream.py
dagstream/executor.py
dagstream/graph_components/__init__.py
dagstream/graph_components/_interface.py
dagstream/graph_components/dags/__init__.py
dagstream/graph_components/dags/functional_dag.py
dagstream/graph_components/dags/interface.py
dagstream/graph_components/edges/__init__.py
dagstream/graph_components/edges/_edge.py
dagstream/graph_components/nodes/__init__.py
dagstream/graph_components/nodes/functional_node.py
dagstream/graph_components/nodes/node_state.py
dagstream/utils/__init__.py
dagstream/utils/errors.py
dagstream/utils/util.py
dagstream/version.py
dagstream/viewers/__init__.py
dagstream/viewers/viewer.py
dagstream-0.1.6.dist-info/LICENSE
dagstream-0.1.6.dist-info/METADATA
dagstream-0.1.6.dist-info/WHEEL
dagstream-0.1.6.dist-info/RECORD
