Metadata-Version: 2.3
Name: dagstream
Version: 0.1.6
Summary: 
License: Apache-2.0
Author: sakamoto
Author-email: sakamoto@ricos.co.jp
Requires-Python: >=3.9,<4.0
Classifier: License :: OSI Approved :: Apache Software License
Classifier: Programming Language :: Python :: 3
Classifier: Programming Language :: Python :: 3.9
Classifier: Programming Language :: Python :: 3.10
Classifier: Programming Language :: Python :: 3.11
Classifier: Programming Language :: Python :: 3.12
Classifier: Programming Language :: Python :: 3.13
Project-URL: Documentation, https://ricosjp.github.io/dagstream/
Project-URL: Homepage, https://github.com/ricosjp/dagstream
Project-URL: Repository, https://github.com/ricosjp/dagstream
